{"version":3,"kind":"Article","sha256":"1a0da9110e4ff89dcf597710e75e2fbe150fa8f1ffd12eb27511e9d7f8d13271","slug":"sensors-and-properties","location":"/explanation/sensors_and_properties.md","dependencies":[],"frontmatter":{"title":"Sensors and Properties","content_includes_title":false,"github":"https://github.com/open223/docs.open223.info","numbering":{"title":{"offset":1}},"source_url":"https://github.com/open223/docs.open223.info/blob/main/explanation/sensors_and_properties.md","edit_url":"https://github.com/open223/docs.open223.info/edit/main/explanation/sensors_and_properties.md","thumbnail":"/build/sensor_platform-fd4b9edf5306701f76f09f729a9284c5.png","exports":[{"format":"md","filename":"sensors_and_properties.md","url":"/build/sensors_and_properti-bd9ba3818d774ad042ffb83d22eaf758.md"}]},"mdast":{"type":"root","children":[{"type":"block","children":[{"type":"paragraph","position":{"start":{"line":3,"column":1},"end":{"line":3,"column":1}},"children":[{"type":"text","value":"The 223 standard defines a variety of specialized sensors defined as a hierarchy of subclasses under the class ","position":{"start":{"line":3,"column":1},"end":{"line":3,"column":1}},"key":"de18SRO8qU"},{"type":"inlineCode","value":"s223:Sensor","position":{"start":{"line":3,"column":1},"end":{"line":3,"column":1}},"key":"KTWhiN4PnY"},{"type":"text","value":". This explanation section discusses some common relationships among sensors, and between sensors and properties.","position":{"start":{"line":3,"column":1},"end":{"line":3,"column":1}},"key":"P054xP24Zh"}],"key":"enX18PwXY8"},{"type":"heading","depth":2,"position":{"start":{"line":5,"column":1},"end":{"line":5,"column":1}},"children":[{"type":"text","value":"Sensors versus Sensor Platforms","position":{"start":{"line":5,"column":1},"end":{"line":5,"column":1}},"key":"aAGdGRahZg"}],"identifier":"sensors-versus-sensor-platforms","label":"Sensors versus Sensor Platforms","html_id":"sensors-versus-sensor-platforms","implicit":true,"key":"zSk61GT88h"},{"type":"paragraph","position":{"start":{"line":6,"column":1},"end":{"line":6,"column":1}},"children":[{"type":"text","value":"The standard constrains an instance of a Sensor to observe a single ","position":{"start":{"line":6,"column":1},"end":{"line":6,"column":1}},"key":"Cj8KmWYuRD"},{"type":"inlineCode","value":"s223:ObservableProperty","position":{"start":{"line":6,"column":1},"end":{"line":6,"column":1}},"key":"vKp5RUZ4Pb"},{"type":"text","value":". Usually it is an instance of the subclass ","position":{"start":{"line":6,"column":1},"end":{"line":6,"column":1}},"key":"GOngXwG7Kk"},{"type":"inlineCode","value":"s223:QuantifiableObservableProperty","position":{"start":{"line":6,"column":1},"end":{"line":6,"column":1}},"key":"h7ZtLldqnk"},{"type":"text","value":" that has a numerical value, but some sensors do generate non-numerical values such as alarms or presence, in which case the property is an instance of ","position":{"start":{"line":6,"column":1},"end":{"line":6,"column":1}},"key":"KcVVq4ZPXC"},{"type":"inlineCode","value":"s223:EnumeratedObservableProperty","position":{"start":{"line":6,"column":1},"end":{"line":6,"column":1}},"key":"oQk0Evhtz1"},{"type":"text","value":".","position":{"start":{"line":6,"column":1},"end":{"line":6,"column":1}},"key":"NpPFnCXW7Y"}],"key":"JDNs82NIG1"},{"type":"paragraph","position":{"start":{"line":8,"column":1},"end":{"line":8,"column":1}},"children":[{"type":"text","value":"Equipment that observes multiple kinds of properties, say temperature and humidity, is modeled as an instance of ","position":{"start":{"line":8,"column":1},"end":{"line":8,"column":1}},"key":"AkValSi1dF"},{"type":"inlineCode","value":"s223:Equipment","position":{"start":{"line":8,"column":1},"end":{"line":8,"column":1}},"key":"lC6nwu9wBZ"},{"type":"text","value":" that contains (","position":{"start":{"line":8,"column":1},"end":{"line":8,"column":1}},"key":"HIKtOKLf67"},{"type":"inlineCode","value":"s223:contains","position":{"start":{"line":8,"column":1},"end":{"line":8,"column":1}},"key":"xAT5mOHHm1"},{"type":"text","value":") an instance of ","position":{"start":{"line":8,"column":1},"end":{"line":8,"column":1}},"key":"NbqWKjOV2K"},{"type":"inlineCode","value":"s223:TemperatureSensor","position":{"start":{"line":8,"column":1},"end":{"line":8,"column":1}},"key":"Uwv5UOlUbr"},{"type":"text","value":" and ","position":{"start":{"line":8,"column":1},"end":{"line":8,"column":1}},"key":"mLzZDFMOB8"},{"type":"inlineCode","value":"s223:HumiditySensor","position":{"start":{"line":8,"column":1},"end":{"line":8,"column":1}},"key":"vkYcbIQRzY"},{"type":"text","value":" respectively.","position":{"start":{"line":8,"column":1},"end":{"line":8,"column":1}},"key":"ZQriE0D0Ci"}],"key":"X0hi8Vroeh"},{"type":"image","url":"/build/sensor_platform-fd4b9edf5306701f76f09f729a9284c5.png","alt":"SensorPlatform","position":{"start":{"line":10,"column":1},"end":{"line":10,"column":1}},"key":"YoR62DTQ86","urlSource":"images/sensor_platform.png"},{"type":"paragraph","position":{"start":{"line":12,"column":1},"end":{"line":12,"column":1}},"children":[{"type":"text","value":"Note that if any of the sensors have ","position":{"start":{"line":12,"column":1},"end":{"line":12,"column":1}},"key":"W8kMuCzDax"},{"type":"inlineCode","value":"s223:ConnectionPoint","position":{"start":{"line":12,"column":1},"end":{"line":12,"column":1}},"key":"LA7BNzvmXb"},{"type":"text","value":"s, the pattern described ","position":{"start":{"line":12,"column":1},"end":{"line":12,"column":1}},"key":"ctb2Px5xVW"},{"type":"link","url":"https://docs.open223.info/guides/design-patterns.html#containment","position":{"start":{"line":12,"column":1},"end":{"line":12,"column":1}},"children":[{"type":"text","value":"here","position":{"start":{"line":12,"column":1},"end":{"line":12,"column":1}},"key":"okwuYY4Cgo"}],"urlSource":"https://docs.open223.info/guides/design-patterns.html#containment","key":"pNCyV1gi6u"},{"type":"text","value":" must also be followed. This might be the case for a flow sensor, for example.","position":{"start":{"line":12,"column":1},"end":{"line":12,"column":1}},"key":"Opv3mlYmcQ"}],"key":"td3lqBPtdv"},{"type":"heading","depth":2,"position":{"start":{"line":14,"column":1},"end":{"line":14,"column":1}},"children":[{"type":"text","value":"Derived Properties","position":{"start":{"line":14,"column":1},"end":{"line":14,"column":1}},"key":"vMxp2lofg9"}],"identifier":"derived-properties","label":"Derived Properties","html_id":"derived-properties","implicit":true,"key":"AhVTBNjE7K"},{"type":"paragraph","position":{"start":{"line":15,"column":1},"end":{"line":15,"column":1}},"children":[{"type":"text","value":"Another constraint in the 223 standard is that an ","position":{"start":{"line":15,"column":1},"end":{"line":15,"column":1}},"key":"gtGU9F7XDB"},{"type":"inlineCode","value":"s223:ObservableProperty","position":{"start":{"line":15,"column":1},"end":{"line":15,"column":1}},"key":"ek26Hbr1kt"},{"type":"text","value":" must be associated with a ","position":{"start":{"line":15,"column":1},"end":{"line":15,"column":1}},"key":"owP1YdCqmm"},{"type":"inlineCode","value":"s223:Sensor","position":{"start":{"line":15,"column":1},"end":{"line":15,"column":1}},"key":"b3WqCdsNoE"},{"type":"text","value":" that observes a phenomenon and generates the value of the property. The sensor ","position":{"start":{"line":15,"column":1},"end":{"line":15,"column":1}},"key":"tk1ub6qzht"},{"type":"inlineCode","value":"s223:observes","position":{"start":{"line":15,"column":1},"end":{"line":15,"column":1}},"key":"FTsoxKV9bO"},{"type":"text","value":" the property.","position":{"start":{"line":15,"column":1},"end":{"line":15,"column":1}},"key":"NKSaPczsMV"}],"key":"CHdvWLjOfo"},{"type":"paragraph","position":{"start":{"line":17,"column":1},"end":{"line":17,"column":1}},"children":[{"type":"text","value":"How does one model a property that is not directly observed by a sensor? This is best modeled using a ","position":{"start":{"line":17,"column":1},"end":{"line":17,"column":1}},"key":"afXqKrQ0KN"},{"type":"inlineCode","value":"s223:Function","position":{"start":{"line":17,"column":1},"end":{"line":17,"column":1}},"key":"AbCnoXe7X4"},{"type":"text","value":" that has one or more input properties (","position":{"start":{"line":17,"column":1},"end":{"line":17,"column":1}},"key":"lN3yVITBxr"},{"type":"inlineCode","value":"s223:hasInput","position":{"start":{"line":17,"column":1},"end":{"line":17,"column":1}},"key":"z52x35tZox"},{"type":"text","value":") and one or more output properties (","position":{"start":{"line":17,"column":1},"end":{"line":17,"column":1}},"key":"zNePa3mtVx"},{"type":"inlineCode","value":"s223:hasOutput","position":{"start":{"line":17,"column":1},"end":{"line":17,"column":1}},"key":"sNXzhgGPAD"},{"type":"text","value":"). The input properties may be directly observed by sensors, or may themselves be the outputs of other functions. The output property would be modeled as an instance of ","position":{"start":{"line":17,"column":1},"end":{"line":17,"column":1}},"key":"T1dyu7Svcd"},{"type":"inlineCode","value":"s223:QuantifiableProperty","position":{"start":{"line":17,"column":1},"end":{"line":17,"column":1}},"key":"Tx87NEDkvY"},{"type":"text","value":" or ","position":{"start":{"line":17,"column":1},"end":{"line":17,"column":1}},"key":"bgGpVlsXCW"},{"type":"inlineCode","value":"s223:EnumerableProperty","position":{"start":{"line":17,"column":1},"end":{"line":17,"column":1}},"key":"BpskeHzdpp"},{"type":"text","value":" as appropriate, but it is not a ","position":{"start":{"line":17,"column":1},"end":{"line":17,"column":1}},"key":"Y7lP5WrOOI"},{"type":"inlineCode","value":"s223:ObservableProperty","position":{"start":{"line":17,"column":1},"end":{"line":17,"column":1}},"key":"kdjb2ScPUJ"},{"type":"text","value":".","position":{"start":{"line":17,"column":1},"end":{"line":17,"column":1}},"key":"YF2kjGnLIe"}],"key":"PwO9tDhz5l"},{"type":"paragraph","position":{"start":{"line":19,"column":1},"end":{"line":19,"column":1}},"children":[{"type":"text","value":"In this way, a model may contain the computed temperature of a room based on some distant sensors and air flow rates for example.","position":{"start":{"line":19,"column":1},"end":{"line":19,"column":1}},"key":"ANmyTKxeFD"}],"key":"tUqN22Mhn5"},{"type":"paragraph","position":{"start":{"line":21,"column":1},"end":{"line":21,"column":1}},"children":[{"type":"text","value":"An example is the ","position":{"start":{"line":21,"column":1},"end":{"line":21,"column":1}},"key":"UUOj0td2kD"},{"type":"inlineCode","value":"psm:VAV1OutletTemperature","position":{"start":{"line":21,"column":1},"end":{"line":21,"column":1}},"key":"NKqzI4OBRH"},{"type":"text","value":" property from the example model found ","position":{"start":{"line":21,"column":1},"end":{"line":21,"column":1}},"key":"Aa4Pl3pMjL"},{"type":"link","url":"https://models.open223.info/examples/nist-bdg1-1.html","position":{"start":{"line":21,"column":1},"end":{"line":21,"column":1}},"children":[{"type":"text","value":"here","position":{"start":{"line":21,"column":1},"end":{"line":21,"column":1}},"key":"WDBxpgu53h"}],"urlSource":"https://models.open223.info/examples/nist-bdg1-1.html","key":"aKGfr6i71u"},{"type":"text","value":".","position":{"start":{"line":21,"column":1},"end":{"line":21,"column":1}},"key":"mJdRwq6aUO"}],"key":"N1m3GxA1j5"},{"type":"image","url":"/build/derived_property-9b58244758b7dcd6ac976be5be2a4b23.png","alt":"DerivedProperty","position":{"start":{"line":23,"column":1},"end":{"line":23,"column":1}},"key":"vwWKiOMkr8","urlSource":"images/derived_property.png"}],"key":"gJCzLjipPS"}],"key":"I4EY8nKh49"},"references":{"cite":{"order":[],"data":{}}},"footer":{"navigation":{"prev":{"title":"Medium Mixtures","url":"/medium-mixtures","group":"Explanation"},"next":{"title":"Model Exploration","url":"/model-exploration","group":"Tutorials"}}},"domain":"http://localhost:3000"}